wavelinkfornextcord/__init__.py
wavelinkfornextcord/backoff.py
wavelinkfornextcord/enums.py
wavelinkfornextcord/exceptions.py
wavelinkfornextcord/ext/spotify/__init__.py
wavelinkfornextcord/filters.py
wavelinkfornextcord/node.py
wavelinkfornextcord/payloads.py
wavelinkfornextcord/player.py
wavelinkfornextcord/queue.py
wavelinkfornextcord/tracks.py
wavelinkfornextcord/types/events.py
wavelinkfornextcord/types/request.py
wavelinkfornextcord/types/state.py
wavelinkfornextcord/types/track.py
wavelinkfornextcord/websocket.py
wavelinkfornextcord-1.0.3.dist-info/METADATA
wavelinkfornextcord-1.0.3.dist-info/WHEEL
wavelinkfornextcord-1.0.3.dist-info/RECORD
