Metadata-Version: 2.1
Name: wavelinkfornextcord
Version: 1.0.3
Summary: All the same wavelink, but based on nextcord! documentation - https://wavelink.readthedocs.io/en/latest
Author: Pythonista
Requires-Python: >=3.10,<4.0
Classifier: Programming Language :: Python :: 3
Classifier: Programming Language :: Python :: 3.10
Classifier: Programming Language :: Python :: 3.11
Requires-Dist: aiohttp (>=3.8.4,<4.0.0)
Requires-Dist: nextcord (>=2.4.1,<3.0.0)
Requires-Dist: yarl (>=1.8.2,<2.0.0)
